page_parser/__init__.py
page_parser/baidu_parser.py
page_parser/douban_parser.py
page_parser/jandan_parser.py
page_parser/jobbole_parser.py
page_parser/lagou_parser.py
page_parser/qichacha_parser.py
page_parser/sogou_parser.py
page_parser/xicidaili_parser.py
page_parser-0.0.4.dist-info/DESCRIPTION.rst
page_parser-0.0.4.dist-info/METADATA
page_parser-0.0.4.dist-info/RECORD
page_parser-0.0.4.dist-info/WHEEL
page_parser-0.0.4.dist-info/metadata.json
page_parser-0.0.4.dist-info/top_level.txt
