Metadata-Version: 2.0
Name: page-parser
Version: 0.0.4
Summary: web crawler or spider parse page
Home-page: https://github.com/mouday/PageParser
Author: Peng Shiyu
Author-email: pengshiyuyx@gmail.com
License: UNKNOWN
Platform: UNKNOWN
Classifier: Programming Language :: Python :: 3
Classifier: License :: OSI Approved :: MIT License
Classifier: Operating System :: OS Independent
Requires-Dist: parsel (>=1.4.0)
Requires-Dist: requests (>=2.18.4)
